{
  "IsEncrypted": false,
  "Values": {
    "AzureWebJobsStorage": "UseDevelopmentStorage=true",
    "AzureWebJobsDashboard": "UseDevelopmentStorage=true",
    // SessionizeReadModelSync
    "SessionizeReadModelSyncSchedule": "* * * * *",
    "SessionsDataSourceType": "Cosmos",
    "SessionsDataSourceCosmosDatabaseId": "Conference",
    "SessionsDataSourceCosmosCollectionId": "Sessions",
    "SessionizeApiKey": "mdhxdmti",
    // NewSessionNotification
    "NewSessionNotificationLogicAppUrl": "http://localhost",
    // EventbriteNotification
    "queue_STORAGE": "UseDevelopmentStorage=true",
    "EventbriteApiBearerToken": "{token}",
    "AZURE_STORAGE_CONNECTION_STRING": "UseDevelopmentStorage=true",
    // GetSubmissions
    "SubmissionsAvailableFrom": "2018-06-05T08:00:00+08:00",
    "SubmissionsAvailableTo": "2018-06-14T23:59:59+08:00",
    "AnonymousSessions": "true"
  },
  "ConnectionStrings": {
    "Sessions": "AccountEndpoint=https://localhost:8081;AccountKey=C2y6yDjf5/R+ob0N8A7Cgv30VRDJIWEHLM+4QDU5DE2nQ9nDuVTqobD4b8mGGyPMbIZnqyMsEcaGQy67XIw/Jw=="
  },
  "Host": {
    "CORS": "*"
  }
}